e_dnevnik_api/__init__.py
e_dnevnik_api/api.py
e_dnevnik_api/errors.py
e_dnevnik_api/helpers.py
e_dnevnik_api-0.1.3.dist-info/LICENSE
e_dnevnik_api-0.1.3.dist-info/METADATA
e_dnevnik_api-0.1.3.dist-info/WHEEL
e_dnevnik_api-0.1.3.dist-info/RECORD
