Metadata-Version: 2.1
Name: e-dnevnik-api
Version: 0.1.3
Summary: Unofficial API for e-Dnevnik
Home-page: https://codeberg.org/ip/e-Dnevnik-API
License: MIT
Author: Ivan Paljetak
Author-email: ip@noreply.codeberg.org
Requires-Python: >=3.10,<4.0
Classifier: License :: OSI Approved :: MIT License
Classifier: Programming Language :: Python :: 3
Classifier: Programming Language :: Python :: 3.10
Classifier: Programming Language :: Python :: 3.11
Requires-Dist: beautifulsoup4 (>=4.11.1,<5.0.0)
Requires-Dist: requests (>=2.28.1,<3.0.0)
Project-URL: Repository, https://codeberg.org/ip/e-Dnevnik-API
